CONTRIBUTING.rst
HISTORY.rst
LICENSE
MANIFEST.in
README.rst
setup.cfg
setup.py
url_encode.py
kupfer_plugin_url_encode.egg-info/PKG-INFO
kupfer_plugin_url_encode.egg-info/SOURCES.txt
kupfer_plugin_url_encode.egg-info/dependency_links.txt
kupfer_plugin_url_encode.egg-info/not-zip-safe
kupfer_plugin_url_encode.egg-info/top_level.txt